setup.cfg
setup.py
trtop/__init__.py
trtop/analyzer.py
trtop/collector.py
trtop/packet.py
trtop/reporter.py
trtop/resolver.py
trtop/state.py
trtop/trtop.py
trtop/utils.py
trtop/whitelisting.py
trtop.egg-info/PKG-INFO
trtop.egg-info/SOURCES.txt
trtop.egg-info/dependency_links.txt
trtop.egg-info/requires.txt
trtop.egg-info/top_level.txt
trtop/tcpdump/__init__.py
trtop/tcpdump/offlinecollector.py
trtop/tcpdump/parser.py