Metadata-Version: 1.0
Name: trtop
Version: 0.1.1
Summary: TCP Remote Top is a tcpdump log visualizer for outgoing connections. It allows monitoring connection/transport latencies as well as QoS (Number of Reqs served for a single connection) for keep-alive sessions. Last, it attempts to detect kernel dropped packets so you know whether to trust the information displayed to you. 
Home-page: UNKNOWN
Author: Thomas Kountis
Author-email: tkountis@gmail.com
License: MIT License
Keywords: tcpdump,trtop,pcap
Platform: Linux
